{"metadata": {"Header 1": "NemKonto", "Header 2": "Tilmelding til NemKonto i Visma Løn", "url": "https://help.vismaenterprise.dk/vismaloen-standard/arbejdsgiver/53-nem-konto", "description": "NemKonto-baseret lønbetaling og viden om deadlines, tilmelding af arbejdsgivere og medarbejdere, og undtagelser for falske CPR-numre.", "primary_keywords": "arbejdsgiver", "Slug": "nem-konto"}, "content": "## Tilmelding til NemKonto i Visma Løn\nFor at kunne anvende NemKonto til lønoverførsler via Visma Løn, skal du tilmelde arbejdsgiveren. Vær opmærksom på, at har I flere arbejdsgivere på jeres kundeforhold, så skal hver enkelt arbejdsgiver tilmeldes.\n* Gå tilArbejdsgiver →Arbejdsgiver stamoplysninger\n* I Løn udbetales via, vælger du NemKonto.Standard står der Anden konto, som betyder, at du overfører via det registrerings- og kontonummer, som I har fået oplyst af medarbejderen.\n* Klik påOK\nNår du har tilmeldt arbejdsgiver, kan du på den enkelte medarbejder fravælge overførsel via NemKonto."}