{"metadata": {"Header 1": "Udbetaling af ferie", "Header 2": "Udbetaling af ferie ved feriehindring", "url": "https://help.vismaenterprise.dk/vismaloen-standard/ferie/69-udbetaling-af-ferie", "description": "Håndtering af udbetaling af feriedage, inklusiv feriekort og 5. ferieuge.", "primary_keywords": "ferie", "Slug": "udbetaling-af-ferie"}, "content": "## Udbetaling af ferie ved feriehindring\nEr feriehindringen sygdom eller orlov efter barselsloven, og består feriehindringen fortsat frem til udgangen af den følgende ferieafholdelsesperiode, kan feriepenge udbetales til medarbejderen.\nUdbetaling sker på baggrund af de Restferiepenge og feriedage/-timer til rådighed, der vises på rapporten ‘Ny ferielov ferieregnskab’. Beregning er, Restferiepenge divideres med restferiedage, og resultatet er udbetaling pr. feriedag.\nFølgende variable lønarter oprettes på medarbejderen, som skal oprettes i debet i kontoplanen på hhv. 40112 og 40113:\n* Lønart 40110 - Udbetaling af feriedage, kontant\n* Lønart 40111 - Udbetaling af ferietimer, kontant"}