{"metadata": {"Header 1": "Arbejdsgiver stamoplysninger", "Header 2": "Felter på arbejdsgiver stamoplysninger", "url": "https://help.vismaenterprise.dk/vismaloen-standard/arbejdsgiver/51-arbejdsgiver-stamoplysninger", "description": "Sådan oprettes en ny arbejdsgiver og en OS-aftale med Mastercard og at udfylde felterne i Visma Løn", "primary_keywords": "arbejdsgiver", "Slug": "arbejdsgiver-stamoplysninger"}, "content": "### Tekst lønseddel\nFeltet kan udfyldes med en tekst, der så udskrives på lønsedlen ved den førstkommende lønkørsel. Efterfølgende slettes teksten. Der kan tastes max. 60 tegn.\n### Feriekort indberetning\nDette felt styrer indberetning til FerieKonto, Feriekort eller Feriekasse. Der kan vælges i mellem følgende:  \n*   Arbejdsgivers CVRnr. – anvendes ved FerieKonto eller Feriekort\n*   Ingen indberetning – feriepengene bliver IKKE indberettet til eIndkomst\n*   Feriekasse/koncern – anvendes ved Feriekasse f.eks. 3F Feriekasse eller en af de 18 feriekasser der findes i Danmark. Se her hvilke feriekasser der findes: [https://skat.dk/skat.aspx?oid=2172361](https://skat.dk/skat.aspx?oid=2172361)\n### Feriekasse/koncern\nHar du i feltet Feriekort indberetning valgt Feriekasse/koncern, skal du i dette felt angive cvr.nr. på feriekassen.\n### Max.træk arb."}