{"metadata": {"Header 1": "Ferietillæg kalenderår", "Header 2": "Ferietillæg – Kalenderår", "url": "https://help.vismaenterprise.dk/vismaloen-standard/ferie/70-ferietillaeg-kalenderar", "description": "Oprettelse af lønarter og kørselsselektioner til udbetaling af ferietillæg og ekstra ferietillæg for kalenderåret samt ferieberettiget grundlag", "primary_keywords": "ferie", "Slug": "ferietillaeg-kalenderar"}, "content": "## Ferietillæg – Kalenderår\nDer er overenskomster som har vedtaget, at opsparing af ferietillæg sker i kalenderåret (01.01 til 31.12) og udbetales typisk i april måned – kørselsordre 12X04.\nEr procenten for ferietillægget en anden end 1%, kan det ændres generelt for en løngruppe på en resultattabel eller det kan ændres personligt på en medarbejder:\n* Resultattabel 4003 - Ferietillæg lovpligtig\n1. Gå tilOpsætning → Resultattabel\n2. Vælg resultattabel 4003\n3. KlikFind\n4. KlikNy periode\n5. Udfyld feltet ‘Gyldig’\n6. KlikOK\n7. VælgResultattrin i højremenuen\n8. KlikNy\n9. Vælg løngruppe og skriv procentsats for aflønningsformen\n10. KlikGem\nØnsker du at ændre ferietillægsprocenten for den enkelte medarbejder, kan du gøre det på:\n* Personlig sats-lønart 9908 – Personlig sats ferietillæg\n1. Gå tilMedarbejder → Ansættelsesforhold\n2. VælgPersonlige satser i højremenuen\n3. KlikNy\n4. Udfyldperiode oglønart\n5. KlikOK"}