{"metadata": {"Header 1": "Pensionsgrundlag", "Header 2": "Pensionsgrundlag 1 (A)", "url": "https://help.vismaenterprise.dk/vismaloen-standard/tillaeg/64-pensionsgrundlag", "description": "Hvilket pensionsgrundlag (A, B, C, og D) den enkelte lønart beregner ud fra og giver mulighed for varianter som tillæg og optjening til fritvalgslønkontoen", "primary_keywords": "tillaeg", "Slug": "pensionsgrundlag"}, "content": "## Pensionsgrundlag 1 (A)\nMånedsløn + pensionsgivende tillæg – fradrag for ferie og – fri egen regning.\nVarianter:Ønskes tillæg, overtid og afspadsering fra følgende lønarter 1010,1300,1307,1330,1331,1370,1371,1410,1430,1700 tillagt pensionsgrundlaget, skal lønart 4303 tilknyttes pågældende stillingskategori.\nØnskes tillæg fra følgende lønarter 1471,1472,1475,1480,1481,1482,1485 tillagt pensionsgrundlaget, skal lønart 4310 tilknyttes pågældende stillingskategori.\nØnskes opsparingen til Fritvalgs Lønkontoen tillagt pensionsgrundlaget, så henvises til vejledningen til Fritvalg."}