{"metadata": {"Header 1": "Særlige dage, timer og beløb", "Header 2": "Opsparing af beløb", "url": "https://help.vismaenterprise.dk/vismaloen-standard/medarbejdertilgode/66-saerlige-dage-timer-og-belob", "description": "Optjening, afholdelse, udbetaling, og hensættelse af særlige dage og timer", "primary_keywords": "medarbejdertilgode", "Slug": "saerlige-dage-timer-og-belob"}, "content": "* 11 = resultattabel (lønartstype 6011 - kun Visma Løn Finans)\n* 20 = Sats pr dag beregnet som 4,8 % af MD løn, ganges med antal dage tildelt.Du kan se lønartstyperne, som indeholder de lønarter der bruges til grundlaget under Opsætning og Lønartstype.Grundlaget du ønsker at anvende skal oprettes på resultattabel:* SSOGRL - Særlige opsparing - GrundlagNår du har angivet det grundlag du ønsker at bruge, skal du på følgende resultattabel angive, hvilken procent du ønsker at opspare af det valgte grundlag. Angiver du 0 eller ikke udfyldt, sker der ingen opsparing:* SSOPCT - Særlige dage / timer opsparing i procentDu kan også vælge, i stedet for at opspare en procent, at opspare til timesatsen eller en fast timesats, som du angiver i denne resultattabel. Så vil de timer der bliver tildelt blive ganget med en af følgende værdier:* 0 eller ikke udfyldt. Ingen opsparing medmindre at der i resultattabel SSOPCT er angivet en procent, som beregnes af den ferieberettigede løn."}