{"metadata": {"Header 1": "Feriefritimer", "Header 2": "Overførsel af feriefri", "url": "https://help.vismaenterprise.dk/vismaloen-standard/ferie/11-feriefritimer", "description": "Administrering af feriefritimer i Visma Løn og information om tildeling, udbetaling og afholdelse af feriefritimer, samt forskellige former for feriefritimer, herunder løbende opsparing af feriefritimer.", "primary_keywords": "ferie", "Slug": "feriefritimer"}, "content": "## Overførsel af feriefri\nAfholdelse af feriefri følger kalenderåret, skal de resterende feriefritimer overføres til nyt kalenderår, kan det gøres ved at bruge variable lønoplysninger eller fællesregistrering.\n* Lønart 311 - feriefritimer overfører saldi fra sidste år"}