{"metadata": {"Header 1": "Arbejdsgiver stamoplysninger", "Header 2": "Skift af bank oplysninger på arbejdsgiver", "url": "https://help.vismaenterprise.dk/vismaloen-standard/arbejdsgiver/51-arbejdsgiver-stamoplysninger", "description": "Sådan oprettes en ny arbejdsgiver og en OS-aftale med Mastercard og at udfylde felterne i Visma Løn", "primary_keywords": "arbejdsgiver", "Slug": "arbejdsgiver-stamoplysninger"}, "content": "vejledning til at hente leverancekvittering, som er gælde fra marts 2024, findes her"}