{"metadata": {"Header 1": "Opsætning af ferietimer/-penge", "Header 2": "Tidsregistreringssystem der leverer ferie fravær i timer", "url": "https://help.vismaenterprise.dk/vismaloen-standard/ferie/75-opsaetning-af-ferietimer-og-feriepenge", "description": "Aspekter vedr. ferieadministration, herunder optjening af ferietimer og feriepenge, afregning af feriepenge, indberetning til Feriepengeinfo og opsætning af systemet til at håndtere feriefravær i timer", "primary_keywords": "ferie", "Slug": "opsaetning-af-ferietimer-og-feriepenge"}, "content": "## Tidsregistreringssystem der leverer ferie fravær i timer\nAnvender du et tidsregistreringssystem der kun kan levere registreringen i timer, men du optjener og afholder ’ferie med løn’ i dage, skal resultattabel:\n* FEFRAV have værdien 1 for de pågældende løngrupper  \nLønsystemet vil omregne ferietimerne til feriedage, ved at tage værdien fra registreringen og dividere med 7,4 timer, svarende til 1 feriedag. Hvis resultattabel TRTIM indeholder en anden værdi, eller den personlige sats lønart 9918 har en anden værdi, så anvendes denne værdi. Resultattabel FEFRAV skal sættes op til håndtering af at registreringen er i timer, der skal omregnes til dage:\n1. Gå tilOpsætning → Resultattabel\n2. Angiv ’FEFRAV’\n3. KlikFind\n4. KlikNy periode\n5. Angiv datoen 01-0X-202X\n6. KlikGem\n7. Vælg Resultattrin i højremenuen\n8. KlikNy\n9. Angiv løngruppe f.eks. F1 og værdien 1 for ferie i timer\n10. KlikGem"}