{"metadata": {"Header 1": "Webinar bibliotek", "Header 2": "Supplerende lønkørsel og egne kørselsordre", "url": "https://help.vismaenterprise.dk/vismaloen-standard/webinars/100-webinar-bibliotek", "description": "I denne vejledning finder du en samlet oversigt over alle webinarer, som Visma Enterprise har lavet til Visma Løn. ", "primary_keywords": "webinars", "Slug": "webinar-bibliotek"}, "content": "## Supplerende lønkørsel og egne kørselsordre\nPå dette webinar gennemgår vi emnerne: supplerende lønkørsel og egne kørselsordrer.\nHar du fået informationer efter din lønkørsel, som du gerne vil udbetale inden din næste almindelige lønkørsel, kan du oprette en supplerende lønkørsel. Har du brug for at køre lønnen for en specifik arbejdsgiver, eller flere udvalgte arbejdsgivere uden at køre løn for samtlige arbejdsgivere på en gang, kan du oprette egne kørselsordrer, og evt. tilpasse standard kørselsordren."}