{"metadata": {"Header 1": "Særlige dage, timer og beløb", "Header 2": "Optjening af særlige dage / timer", "url": "https://help.vismaenterprise.dk/vismaloen-standard/medarbejdertilgode/66-saerlige-dage-timer-og-belob", "description": "Optjening, afholdelse, udbetaling, og hensættelse af særlige dage og timer", "primary_keywords": "medarbejdertilgode", "Slug": "saerlige-dage-timer-og-belob"}, "content": "Er årligt du skal opspare 5 særlige dage, og du i resultattabel SSO har angivet at det er en årlig tildeling, skal du i denne resultattabel oprette 5 særlige dage:\nSærlige dage, oprettes i resultattabel:\n* SÆRDG - Særlige dage tildeling\nØnsker du at anvende særlige timer i stedet for særlige dage, opretter du følgende resultattabel med det antal timer der skal opspares årligt eller i hver lønkørsel:\n* SÆRTI - Særlige timer tildeling\nSådan opretter du ovenstående resultattabeller:\n1. Gå tilOpsætning → Resultattabel\n2. Angiv en af ovenstående resultattabeller\n3. KlikFind\n4. KlikNy periode\n5. Udfyld feltet ’Gyldig’\n6. KlikOK\n7. VælgResultattrin i højremenuen\n8. KlikNy\n9. Vælg løngruppen og værdien for aflønningsformen\n10. KlikGem\n11. Gentag ovenstående for den næste resultattabel"}