{"metadata": {"Header 1": "Ekstra “feriedage” udover ferielovens 25 feriedage", "url": "https://help.vismaenterprise.dk/vismaloen-standard/ferie/26-ekstra-feriedage-udover-ferielovens-25-feriedage", "description": "Informerer og viser hvordan der betales og tildeles fridage, udover de 25 feriedage, reguleret af overenskomster eller individuelle aftaler mellem virksomheden og medarbejderen", "primary_keywords": "ferie", "Slug": "ekstra-feriedage-udover-ferielovens-25-feriedage"}, "content": "Har du spørgsmål eller brug for hjælp af en konsulent fra Visma Enterprise, kan du ringe til os på tlf. 88 97 97 00."}