{"metadata": {"Header 1": "Efterregulering", "Header 2": "Sådan bruger du efterregulering", "url": "https://help.vismaenterprise.dk/vismaloen-standard/lonkorsel/13-efterregulering", "description": "Reguler løn, skat og øvrige satser tilbage i tid for indeværende år, på godkendte lønkørsler, med korrekt indberetning til eIndkomst.", "primary_keywords": "lonkorsel", "Slug": "efterregulering"}, "content": "Opsætning med efterregulering\nI skærmbilledet ’Opsætning med efterregulering’ kan du se, hvilke resultattabeller, stillingskategorier eller generelle satser, der er markeret til at blive efterreguleret. Derudover vises hvilken dato efterreguleringen vil ske fra, samt hvem der har opdateret rettelsen.\nEr der en * markering efter tabellens navn betyder det, at der endnu ikke har været kørt en efterregulering, hvor den pågældende tabel har været med. Er tabellen IKKE markeret med * markering har en efterregulering været annulleret, og evt. berørte medarbejdere er nu også vist i skærmbilledet ’Medarbejder med efterregulering’.\nFjern efterregulering på opsætning\nDet er muligt at fjerne en efterreguleringsdato på en opsætningstabel, der er forsynet med * markering efter tabellens navn (- betyder at tabellen ikke har været med i en efterregulering).\n1. Gå tilGå tilLønadministration →Opsætn.m.efterreg.\n2. Dobbeltklik på tabellen\n3. Klik påFjern"}