{"metadata": {"Header 1": "Webinar bibliotek", "Header 2": "Ferie på elever - særlige dage", "url": "https://help.vismaenterprise.dk/vismaloen-standard/webinars/100-webinar-bibliotek", "description": "I denne vejledning finder du en samlet oversigt over alle webinarer, som Visma Enterprise har lavet til Visma Løn. ", "primary_keywords": "webinars", "Slug": "webinar-bibliotek"}, "content": "## Ferie på elever - særlige dage\nOptjening af ferie på elever/lærlinge, som har ferie med løn. Elever der er ansat den 2. september eller senere skal have tildelt 25 feriedage og samtidig optjene samtidighedsferie. På dette webinar vil du se hvordan du kan sætte Visma Løn op til at kunne håndtere både tildelte feriedage og samtidighedsferie."}